imdb_lib/__init__.py
imdb_lib/imdb_lib_test.py
imdb_lib/session.py
imdb_lib-0.3.dist-info/LICENSE
imdb_lib-0.3.dist-info/METADATA
imdb_lib-0.3.dist-info/WHEEL
imdb_lib-0.3.dist-info/top_level.txt
imdb_lib-0.3.dist-info/RECORD
