Metadata-Version: 2.1
Name: imdb-lib
Version: 0.3
Summary: Web Scraping data from imdb website.
Home-page: https://github.com/ricardobohadana/imdb_lib
Author: Ricardo Bohadana Martins
Author-email: bmartinsricardo@gmail.com
License: UNKNOWN
Platform: UNKNOWN
Classifier: Programming Language :: Python :: 3
Classifier: License :: OSI Approved :: MIT License
Classifier: Operating System :: OS Independent
Requires-Python: >=3.7
License-File: LICENSE
